[
  {
    "apply": [
      "geo:DescribeGeofenceCollection",
      "geo:CreateGeofenceCollection",
      "geo:DeleteGeofenceCollection",
      "geo:UpdateGeofenceCollection"
    ],
    "attributes": {
      "kms_key_id": [
        "kms:DescribeKey",
        "kms:CreateGrant"
      ],
      "tags": [
        "geo:TagResource",
        "geo:UntagResource"
      ]
    },
    "destroy": [
      "geo:DeleteGeofenceCollection"
    ],
    "modify": [
      "geo:UpdateGeofenceCollection"
    ],
    "plan": []
  }
]
